{
  "version": "1.1.0",
  "description": "Example for a womenswear ecommerce app.",
  "totalFinalAssets": 5,
  "totalMasterAssets": 1,
  "totalManifestItems": 6,
  "rules": [
    "single: one prompt generates one final asset.",
    "group_variant: one prompt group generates multiple clearly named variants.",
    "single_master: generate one master asset, then reuse/crop for multiple pages.",
    "reuse or reuse_crop: do not regenerate; derive from reuseSource."
  ],
  "assets": [
    {
      "assetName": "home_banner_aw_collection",
      "page": "home",
      "assetType": "banner",
      "outputPath": "/static/images/banner/home_banner_aw_collection.png",
      "recommendedSize": "1380x600",
      "transparent": false,
      "generationMode": "single",
      "promptGroup": "home_banner_aw_collection",
      "promptGroupOutputCount": 1,
      "variantIndex": 1,
      "variantName": "two_models_autumn_winter_commuter_banner",
      "reuseSource": null,
      "styleDifference": "Two models on the right, blank area on the left.",
      "frontEndUsage": "Hero banner background."
    },
    {
      "assetName": "white_coat_product_master",
      "page": "shared",
      "assetType": "product",
      "outputPath": "/static/images/product/white_coat_product_master.png",
      "recommendedSize": "1500x1500",
      "transparent": false,
      "generationMode": "single_master",
      "promptGroup": "white_coat_product",
      "promptGroupOutputCount": 1,
      "variantIndex": 1,
      "variantName": "cream_wool_blend_blazer_model",
      "reuseSource": null,
      "styleDifference": "Master product image for reuse.",
      "frontEndUsage": "Shared product image source."
    },
    {
      "assetName": "home_product_white_coat",
      "page": "home",
      "assetType": "product",
      "outputPath": "/static/images/product/home_product_white_coat.png",
      "recommendedSize": "1200x1200",
      "transparent": false,
      "generationMode": "reuse_crop",
      "promptGroup": "white_coat_product",
      "promptGroupOutputCount": 1,
      "variantIndex": 1,
      "variantName": "home_square_crop",
      "reuseSource": "white_coat_product_master",
      "styleDifference": "Square crop for home product card.",
      "frontEndUsage": "Home product card image."
    },
    {
      "assetName": "category_short_blazer",
      "page": "category",
      "assetType": "category",
      "outputPath": "/static/images/category/category_short_blazer.png",
      "recommendedSize": "600x600",
      "transparent": true,
      "generationMode": "group_variant",
      "promptGroup": "category_single_blazers",
      "promptGroupOutputCount": 2,
      "variantIndex": 1,
      "variantName": "short_black_blazer",
      "reuseSource": null,
      "styleDifference": "Short black blazer.",
      "frontEndUsage": "Category entry image."
    },
    {
      "assetName": "category_boxy_blazer",
      "page": "category",
      "assetType": "category",
      "outputPath": "/static/images/category/category_boxy_blazer.png",
      "recommendedSize": "600x600",
      "transparent": true,
      "generationMode": "group_variant",
      "promptGroup": "category_single_blazers",
      "promptGroupOutputCount": 2,
      "variantIndex": 2,
      "variantName": "boxy_beige_blazer",
      "reuseSource": null,
      "styleDifference": "Boxy beige blazer.",
      "frontEndUsage": "Category entry image."
    },
    {
      "assetName": "profile_outfit_banner",
      "page": "profile",
      "assetType": "banner",
      "outputPath": "/static/images/banner/profile_outfit_banner.png",
      "recommendedSize": "1380x420",
      "transparent": false,
      "generationMode": "single",
      "promptGroup": "profile_outfit_banner",
      "promptGroupOutputCount": 1,
      "variantIndex": 1,
      "variantName": "weekly_outfit_flatlay",
      "reuseSource": null,
      "styleDifference": "Flat lay outfit banner.",
      "frontEndUsage": "Profile recommendation banner."
    }
  ]
}
